basic_decorators/__init__.py
basic_decorators-1.0.6.data/data/requirements.txt
basic_decorators-1.0.6.data/data/.git/config
basic_decorators-1.0.6.dist-info/LICENSE
basic_decorators-1.0.6.dist-info/METADATA
basic_decorators-1.0.6.dist-info/WHEEL
basic_decorators-1.0.6.dist-info/top_level.txt
basic_decorators-1.0.6.dist-info/RECORD
