Metadata-Version: 2.1
Name: basic-decorators
Version: 1.0.6
Summary: basic_decorators: Repository with usefull decorator methods
Home-page: https://github.com/R-Rijnbeek/basic_decorators
Author: Robert Rijnbeek
Author-email: robert270384@gmail.com
Project-URL: Bug Tracker, https://github.com/R-Rijnbeek/basic_decorators/issues
Classifier: Programming Language :: Python :: 3
Classifier: License :: OSI Approved :: MIT License
Classifier: Operating System :: OS Independent
Requires-Python: >=3.6
License-File: LICENSE
